{
	"Id": "Lootable_00068",
	"IsStatic": true,
	"useGravity": true,
	"randomRotation": false,
	"Position": {
		"x": 0,
		"y": 0,
		"z": 0
	},
	"Rotation": {
		"x": 0,
		"y": 0,
		"z": 0
	},
	"IsGroupPosition": false,
	"GroupPositions": [],
	"Root": "5e68b2a286f77406711e638c",
	"Items": [
		{
			"_id": "5e68b2a286f77406711e638c",
			"_tpl": "5d6d2b5486f774785c2ba8ea"
		},
		{
			"_id": "5e68b2a286f77406711e638d",
			"_tpl": "5e2aee0a86f774755a234b62",
			"parentId": "5e68b2a286f77406711e638c",
			"slotId": "main",
			"location": {
				"x": 0,
				"y": 0,
				"r": 0
			}
		},
		{
			"_id": "5e68b2a286f77406711e638e",
			"_tpl": "590a3c0a86f774385a33c450",
			"parentId": "5e68b2a286f77406711e638c",
			"slotId": "main",
			"location": {
				"x": 2,
				"y": 0,
				"r": 0
			}
		},
		{
			"_id": "5e68b2a286f77406711e638f",
			"_tpl": "560d61e84bdc2da74d8b4571",
			"parentId": "5e68b2a286f77406711e638c",
			"slotId": "main",
			"location": {
				"x": 3,
				"y": 0,
				"r": 0
			},
			"upd": {
				"StackObjectsCount": 17
			}
		},
		{
			"_id": "5e68b2a286f77406711e6390",
			"_tpl": "5672cb124bdc2d1a0f8b4568",
			"parentId": "5e68b2a286f77406711e638c",
			"slotId": "main",
			"location": {
				"x": 0,
				"y": 1,
				"r": 0
			}
		},
		{
			"_id": "5e68b2a286f77406711e6391",
			"_tpl": "544fb62a4bdc2dfb738b4568",
			"parentId": "5e68b2a286f77406711e638c",
			"slotId": "main",
			"location": {
				"x": 1,
				"y": 1,
				"r": 0
			}
		},
		{
			"_id": "5e68b2a286f77406711e6392",
			"_tpl": "57347d9c245977448b40fa85",
			"parentId": "5e68b2a286f77406711e638c",
			"slotId": "main",
			"location": {
				"x": 2,
				"y": 1,
				"r": 0
			}
		}
	]
}