{
	"Id": "Lootable_00226",
	"IsStatic": true,
	"useGravity": true,
	"randomRotation": false,
	"Position": {
		"x": 0,
		"y": 0,
		"z": 0
	},
	"Rotation": {
		"x": 0,
		"y": 0,
		"z": 0
	},
	"IsGroupPosition": false,
	"GroupPositions": [],
	"Root": "5e68b2b086f7745c3c43f4e0",
	"Items": [
		{
			"_id": "5e68b2b086f7745c3c43f4e0",
			"_tpl": "5909d5ef86f77467974efbd8"
		},
		{
			"_id": "5e68b2b086f7745c3c43f4e1",
			"_tpl": "5648b1504bdc2d9d488b4584",
			"parentId": "5e68b2b086f7745c3c43f4e0",
			"slotId": "main",
			"location": {
				"x": 0,
				"y": 0,
				"r": 0
			}
		}
	]
}