{
	"Id": "Lootable_00058",
	"IsStatic": true,
	"useGravity": true,
	"randomRotation": false,
	"Position": {
		"x": 0,
		"y": 0,
		"z": 0
	},
	"Rotation": {
		"x": 0,
		"y": 0,
		"z": 0
	},
	"IsGroupPosition": false,
	"GroupPositions": [],
	"Root": "5e68b2df86f77406711e70bd",
	"Items": [
		{
			"_id": "5e68b2df86f77406711e70bd",
			"_tpl": "578f87b7245977356274f2cd"
		},
		{
			"_id": "5e68b2df86f77406711e70be",
			"_tpl": "590a3c0a86f774385a33c450",
			"parentId": "5e68b2df86f77406711e70bd",
			"slotId": "main",
			"location": {
				"x": 0,
				"y": 0,
				"r": 0
			}
		},
		{
			"_id": "5e68b2df86f77406711e70bf",
			"_tpl": "590a3c0a86f774385a33c450",
			"parentId": "5e68b2df86f77406711e70bd",
			"slotId": "main",
			"location": {
				"x": 1,
				"y": 0,
				"r": 0
			}
		}
	]
}