{
	"Id": "loot_mods (130)8357318",
	"IsStatic": false,
	"useGravity": true,
	"randomRotation": true,
	"Position": {
		"x": -24.6435547,
		"y": 28.2798119,
		"z": -124.309326
	},
	"Rotation": {
		"x": 0,
		"y": 0,
		"z": 0
	},
	"IsGroupPosition": false,
	"GroupPositions": [],
	"Root": "5e68b2cb86f7745c3c43f8b0",
	"Items": [
		{
			"_id": "5e68b2cb86f7745c3c43f8b0",
			"_tpl": "5aaa5dfee5b5b000140293d3"
		},
		{
			"_id": "5e68b2cb86f7745c3c43f8b1",
			"_tpl": "59e6920f86f77411d82aa167",
			"parentId": "5e68b2cb86f7745c3c43f8b0",
			"slotId": "cartridges",
			"upd": {
				"StackObjectsCount": 13
			}
		}
	]
}