{
	"Id": "Lootable_00007",
	"IsStatic": true,
	"useGravity": true,
	"randomRotation": false,
	"Position": {
		"x": 0,
		"y": 0,
		"z": 0
	},
	"Rotation": {
		"x": 0,
		"y": 0,
		"z": 0
	},
	"IsGroupPosition": false,
	"GroupPositions": [],
	"Root": "5e68b28d86f7745c3a08fa16",
	"Items": [
		{
			"_id": "5e68b28d86f7745c3a08fa16",
			"_tpl": "578f87ad245977356274f2cc"
		},
		{
			"_id": "5e68b28d86f7745c3a08fa17",
			"_tpl": "5448be9a4bdc2dfd2f8b456a",
			"parentId": "5e68b28d86f7745c3a08fa16",
			"slotId": "main",
			"location": {
				"x": 0,
				"y": 0,
				"r": 0
			}
		},
		{
			"_id": "5e68b28d86f7745c3a08fa18",
			"_tpl": "5a9fb739a2750c003215717f",
			"parentId": "5e68b28d86f7745c3a08fa16",
			"slotId": "main",
			"location": {
				"x": 1,
				"y": 0,
				"r": 0
			}
		}
	]
}