{
	"Id": "Lootable_00014",
	"IsStatic": true,
	"useGravity": true,
	"randomRotation": false,
	"Position": {
		"x": 0,
		"y": 0,
		"z": 0
	},
	"Rotation": {
		"x": 0,
		"y": 0,
		"z": 0
	},
	"IsGroupPosition": false,
	"GroupPositions": [],
	"Root": "5e68b2a386f77406711e6413",
	"Items": [
		{
			"_id": "5e68b2a386f77406711e6413",
			"_tpl": "5909d89086f77472591234a0"
		},
		{
			"_id": "5e68b2a386f77406711e6414",
			"_tpl": "59ff346386f77477562ff5e2",
			"parentId": "5e68b2a386f77406711e6413",
			"slotId": "main",
			"location": {
				"x": 0,
				"y": 0,
				"r": 0
			}
		},
		{
			"_id": "5e68b2a386f77406711e6415",
			"_tpl": "59d64ec286f774171d1e0a42",
			"parentId": "5e68b2a386f77406711e6414",
			"slotId": "mod_gas_block"
		},
		{
			"_id": "5e68b2a386f77406711e641c",
			"_tpl": "59d64f2f86f77417193ef8b3",
			"parentId": "5e68b2a386f77406711e6415",
			"slotId": "mod_handguard"
		},
		{
			"_id": "5e68b2a386f77406711e6416",
			"_tpl": "59d64fc686f774171b243fe2",
			"parentId": "5e68b2a386f77406711e6414",
			"slotId": "mod_muzzle"
		},
		{
			"_id": "5e68b2a386f77406711e6417",
			"_tpl": "5a0071d486f77404e23a12b2",
			"parentId": "5e68b2a386f77406711e6414",
			"slotId": "mod_pistol_grip_akms"
		},
		{
			"_id": "5e68b2a386f77406711e6418",
			"_tpl": "59d6507c86f7741b846413a2",
			"parentId": "5e68b2a386f77406711e6414",
			"slotId": "mod_reciever"
		},
		{
			"_id": "5e68b2a386f77406711e6419",
			"_tpl": "59d650cf86f7741b846413a4",
			"parentId": "5e68b2a386f77406711e6414",
			"slotId": "mod_sight_rear"
		},
		{
			"_id": "5e68b2a386f77406711e641a",
			"_tpl": "59ff3b6a86f77477562ff5ed",
			"parentId": "5e68b2a386f77406711e6414",
			"slotId": "mod_stock_akms"
		},
		{
			"_id": "5e68b2a386f77406711e641b",
			"_tpl": "5a0060fc86f7745793204432",
			"parentId": "5e68b2a386f77406711e6414",
			"slotId": "mod_magazine"
		},
		{
			"_id": "5e68b2a386f77406711e641d",
			"_tpl": "5656d7c34bdc2d9d198b4587",
			"parentId": "5e68b2a386f77406711e641b",
			"slotId": "cartridges",
			"upd": {
				"StackObjectsCount": 14
			}
		},
		{
			"_id": "5e68b2a386f77406711e641e",
			"_tpl": "5649af094bdc2df8348b4586",
			"parentId": "5e68b2a386f77406711e6413",
			"slotId": "main",
			"location": {
				"x": 0,
				"y": 2,
				"r": 0
			}
		}
	]
}