{
	"Id": "Lootable_00024",
	"IsStatic": true,
	"useGravity": true,
	"randomRotation": false,
	"Position": {
		"x": 0,
		"y": 0,
		"z": 0
	},
	"Rotation": {
		"x": 0,
		"y": 0,
		"z": 0
	},
	"IsGroupPosition": false,
	"GroupPositions": [],
	"Root": "5e68b2b886f77466494291c7",
	"Items": [
		{
			"_id": "5e68b2b886f77466494291c7",
			"_tpl": "578f8782245977354405a1e3"
		},
		{
			"_id": "5e68b2b886f77466494291c8",
			"_tpl": "590de71386f774347051a052",
			"parentId": "5e68b2b886f77466494291c7",
			"slotId": "main",
			"location": {
				"x": 0,
				"y": 0,
				"r": 0
			}
		},
		{
			"_id": "5e68b2b886f77466494291c9",
			"_tpl": "5449016a4bdc2d6f028b456f",
			"parentId": "5e68b2b886f77466494291c7",
			"slotId": "main",
			"location": {
				"x": 1,
				"y": 0,
				"r": 0
			},
			"upd": {
				"StackObjectsCount": 1101
			}
		},
		{
			"_id": "5e68b2b886f77466494291ca",
			"_tpl": "5449016a4bdc2d6f028b456f",
			"parentId": "5e68b2b886f77466494291c7",
			"slotId": "main",
			"location": {
				"x": 2,
				"y": 0,
				"r": 0
			},
			"upd": {
				"StackObjectsCount": 903
			}
		},
		{
			"_id": "5e68b2b886f77466494291cb",
			"_tpl": "5449016a4bdc2d6f028b456f",
			"parentId": "5e68b2b886f77466494291c7",
			"slotId": "main",
			"location": {
				"x": 1,
				"y": 1,
				"r": 0
			},
			"upd": {
				"StackObjectsCount": 735
			}
		},
		{
			"_id": "5e68b2b886f77466494291cc",
			"_tpl": "5449016a4bdc2d6f028b456f",
			"parentId": "5e68b2b886f77466494291c7",
			"slotId": "main",
			"location": {
				"x": 2,
				"y": 1,
				"r": 0
			},
			"upd": {
				"StackObjectsCount": 884
			}
		},
		{
			"_id": "5e68b2b886f77466494291cd",
			"_tpl": "5449016a4bdc2d6f028b456f",
			"parentId": "5e68b2b886f77466494291c7",
			"slotId": "main",
			"location": {
				"x": 0,
				"y": 2,
				"r": 0
			},
			"upd": {
				"StackObjectsCount": 722
			}
		}
	]
}