{
	"Id": "loot_mix_food_med_ammo (95)4560102",
	"IsStatic": false,
	"useGravity": true,
	"randomRotation": true,
	"Position": {
		"x": -217.927,
		"y": 4.76,
		"z": -355.596
	},
	"Rotation": {
		"x": 0,
		"y": 0,
		"z": 0
	},
	"IsGroupPosition": false,
	"GroupPositions": [],
	"Root": "5e68b2db86f7741caf48c71b",
	"Items": [
		{
			"_id": "5e68b2db86f7741caf48c71b",
			"_tpl": "573725b0245977612125bae2"
		},
		{
			"_id": "5e68b2db86f7741caf48c71c",
			"_tpl": "57371b192459775a9f58a5e0",
			"parentId": "5e68b2db86f7741caf48c71b",
			"slotId": "cartridges",
			"upd": {
				"StackObjectsCount": 16
			}
		}
	]
}