{
	"Id": "Lootable_00182",
	"IsStatic": true,
	"useGravity": true,
	"randomRotation": false,
	"Position": {
		"x": 0,
		"y": 0,
		"z": 0
	},
	"Rotation": {
		"x": 0,
		"y": 0,
		"z": 0
	},
	"IsGroupPosition": false,
	"GroupPositions": [],
	"Root": "5e68b2c086f7741caf48c0b3",
	"Items": [
		{
			"_id": "5e68b2c086f7741caf48c0b3",
			"_tpl": "5909d5ef86f77467974efbd8"
		},
		{
			"_id": "5e68b2c086f7741caf48c0b4",
			"_tpl": "57d17c5e2459775a5c57d17d",
			"parentId": "5e68b2c086f7741caf48c0b3",
			"slotId": "main",
			"location": {
				"x": 0,
				"y": 0,
				"r": 0
			}
		},
		{
			"_id": "5e68b2c086f7741caf48c0b5",
			"_tpl": "59db3b0886f77429d72fb895",
			"parentId": "5e68b2c086f7741caf48c0b3",
			"slotId": "main",
			"location": {
				"x": 1,
				"y": 0,
				"r": 0
			}
		},
		{
			"_id": "5e68b2c086f7741caf48c0b6",
			"_tpl": "5a6f5e048dc32e00094b97da",
			"parentId": "5e68b2c086f7741caf48c0b3",
			"slotId": "main",
			"location": {
				"x": 2,
				"y": 0,
				"r": 0
			}
		}
	]
}