{
	"Id": "Lootable_00057",
	"IsStatic": true,
	"useGravity": true,
	"randomRotation": false,
	"Position": {
		"x": 0,
		"y": 0,
		"z": 0
	},
	"Rotation": {
		"x": 0,
		"y": 0,
		"z": 0
	},
	"IsGroupPosition": false,
	"GroupPositions": [],
	"Root": "5e68b27b86f7745c3b243106",
	"Items": [
		{
			"_id": "5e68b27b86f7745c3b243106",
			"_tpl": "5909d89086f77472591234a0"
		},
		{
			"_id": "5e68b27b86f7745c3b243107",
			"_tpl": "56d5a661d2720bd8418b456b",
			"parentId": "5e68b27b86f7745c3b243106",
			"slotId": "main",
			"location": {
				"x": 0,
				"y": 0,
				"r": 0
			}
		},
		{
			"_id": "5e68b27b86f7745c3b243108",
			"_tpl": "544a378f4bdc2d30388b4567",
			"parentId": "5e68b27b86f7745c3b243106",
			"slotId": "main",
			"location": {
				"x": 1,
				"y": 0,
				"r": 0
			}
		},
		{
			"_id": "5e68b27b86f7745c3b243109",
			"_tpl": "59e6687d86f77411d949b251",
			"parentId": "5e68b27b86f7745c3b243106",
			"slotId": "main",
			"location": {
				"x": 2,
				"y": 0,
				"r": 1
			}
		},
		{
			"_id": "5e68b27b86f7745c3b24310a",
			"_tpl": "59e649f986f77411d949b246",
			"parentId": "5e68b27b86f7745c3b243109",
			"slotId": "mod_gas_block"
		},
		{
			"_id": "5e68b27b86f7745c3b243111",
			"_tpl": "59e898ee86f77427614bd225",
			"parentId": "5e68b27b86f7745c3b24310a",
			"slotId": "mod_handguard"
		},
		{
			"_id": "5e68b27b86f7745c3b24310b",
			"_tpl": "59e8a00d86f7742ad93b569c",
			"parentId": "5e68b27b86f7745c3b243109",
			"slotId": "mod_muzzle"
		},
		{
			"_id": "5e68b27b86f7745c3b24310c",
			"_tpl": "59e6318286f77444dd62c4cc",
			"parentId": "5e68b27b86f7745c3b243109",
			"slotId": "mod_pistol_grip"
		},
		{
			"_id": "5e68b27b86f7745c3b24310d",
			"_tpl": "59e6449086f7746c9f75e822",
			"parentId": "5e68b27b86f7745c3b243109",
			"slotId": "mod_reciever"
		},
		{
			"_id": "5e68b27b86f7745c3b24310e",
			"_tpl": "59e8977386f77415a553c453",
			"parentId": "5e68b27b86f7745c3b243109",
			"slotId": "mod_sight_rear"
		},
		{
			"_id": "5e68b27b86f7745c3b24310f",
			"_tpl": "59e89d0986f77427600d226e",
			"parentId": "5e68b27b86f7745c3b243109",
			"slotId": "mod_stock"
		},
		{
			"_id": "5e68b27b86f7745c3b243110",
			"_tpl": "59d625f086f774661516605d",
			"parentId": "5e68b27b86f7745c3b243109",
			"slotId": "mod_magazine"
		},
		{
			"_id": "5e68b27b86f7745c3b243112",
			"_tpl": "59e6542b86f77411dc52a77a",
			"parentId": "5e68b27b86f7745c3b243110",
			"slotId": "cartridges",
			"upd": {
				"StackObjectsCount": 20
			}
		}
	]
}