{
	"Id": "Lootable_00030",
	"IsStatic": true,
	"useGravity": true,
	"randomRotation": false,
	"Position": {
		"x": 0,
		"y": 0,
		"z": 0
	},
	"Rotation": {
		"x": 0,
		"y": 0,
		"z": 0
	},
	"IsGroupPosition": false,
	"GroupPositions": [],
	"Root": "5e68b26d86f77406711e5da1",
	"Items": [
		{
			"_id": "5e68b26d86f77406711e5da1",
			"_tpl": "578f8778245977358849a9b5"
		},
		{
			"_id": "5e68b26d86f77406711e5da2",
			"_tpl": "57347d3d245977448f7b7f61",
			"parentId": "5e68b26d86f77406711e5da1",
			"slotId": "main",
			"location": {
				"x": 0,
				"y": 0,
				"r": 0
			}
		}
	]
}