{
	"Id": "Lootable_00298",
	"IsStatic": true,
	"useGravity": true,
	"randomRotation": false,
	"Position": {
		"x": 0,
		"y": 0,
		"z": 0
	},
	"Rotation": {
		"x": 0,
		"y": 0,
		"z": 0
	},
	"IsGroupPosition": false,
	"GroupPositions": [],
	"Root": "5e68b2fb86f7741caf48d142",
	"Items": [
		{
			"_id": "5e68b2fb86f7741caf48d142",
			"_tpl": "59139c2186f77411564f8e42"
		},
		{
			"_id": "5e68b2fb86f7741caf48d143",
			"_tpl": "5c06782b86f77426df5407d2",
			"parentId": "5e68b2fb86f7741caf48d142",
			"slotId": "main",
			"location": {
				"x": 0,
				"y": 0,
				"r": 0
			}
		}
	]
}