{
	"Id": "Lootable_00412",
	"IsStatic": true,
	"useGravity": true,
	"randomRotation": false,
	"Position": {
		"x": 0,
		"y": 0,
		"z": 0
	},
	"Rotation": {
		"x": 0,
		"y": 0,
		"z": 0
	},
	"IsGroupPosition": false,
	"GroupPositions": [],
	"Root": "5e68b2c386f7745c3a0902a0",
	"Items": [
		{
			"_id": "5e68b2c386f7745c3a0902a0",
			"_tpl": "5d6d2bb386f774785b07a77a"
		},
		{
			"_id": "5e68b2c386f7745c3a0902a1",
			"_tpl": "5751435d24597720a27126d1",
			"parentId": "5e68b2c386f7745c3a0902a0",
			"slotId": "main",
			"location": {
				"x": 0,
				"y": 0,
				"r": 0
			}
		},
		{
			"_id": "5e68b2c386f7745c3a0902a2",
			"_tpl": "5bc9c29cd4351e003562b8a3",
			"parentId": "5e68b2c386f7745c3a0902a0",
			"slotId": "main",
			"location": {
				"x": 1,
				"y": 0,
				"r": 0
			}
		},
		{
			"_id": "5e68b2c386f7745c3a0902a3",
			"_tpl": "54527a984bdc2d4e668b4567",
			"parentId": "5e68b2c386f7745c3a0902a0",
			"slotId": "main",
			"location": {
				"x": 2,
				"y": 0,
				"r": 0
			},
			"upd": {
				"StackObjectsCount": 7
			}
		},
		{
			"_id": "5e68b2c386f7745c3a0902a4",
			"_tpl": "575146b724597720a27126d5",
			"parentId": "5e68b2c386f7745c3a0902a0",
			"slotId": "main",
			"location": {
				"x": 0,
				"y": 1,
				"r": 0
			}
		},
		{
			"_id": "5e68b2c386f7745c3a0902a5",
			"_tpl": "573476d324597737da2adc13",
			"parentId": "5e68b2c386f7745c3a0902a0",
			"slotId": "main",
			"location": {
				"x": 1,
				"y": 1,
				"r": 0
			}
		},
		{
			"_id": "5e68b2c386f7745c3a0902a6",
			"_tpl": "56dff0bed2720bb0668b4567",
			"parentId": "5e68b2c386f7745c3a0902a0",
			"slotId": "main",
			"location": {
				"x": 2,
				"y": 1,
				"r": 0
			},
			"upd": {
				"StackObjectsCount": 9
			}
		},
		{
			"_id": "5e68b2c386f7745c3a0902a7",
			"_tpl": "59e6918f86f7746c9f75e849",
			"parentId": "5e68b2c386f7745c3a0902a0",
			"slotId": "main",
			"location": {
				"x": 1,
				"y": 2,
				"r": 0
			},
			"upd": {
				"StackObjectsCount": 13
			}
		}
	]
}