{
	"Id": "Lootable_00261",
	"IsStatic": true,
	"useGravity": true,
	"randomRotation": false,
	"Position": {
		"x": 0,
		"y": 0,
		"z": 0
	},
	"Rotation": {
		"x": 0,
		"y": 0,
		"z": 0
	},
	"IsGroupPosition": false,
	"GroupPositions": [],
	"Root": "5e68b2c286f7745c3a0901ee",
	"Items": [
		{
			"_id": "5e68b2c286f7745c3a0901ee",
			"_tpl": "578f87a3245977356274f2cb"
		},
		{
			"_id": "5e68b2c286f7745c3a0901ef",
			"_tpl": "56742c2e4bdc2d95058b456d",
			"parentId": "5e68b2c286f7745c3a0901ee",
			"slotId": "main",
			"location": {
				"x": 0,
				"y": 0,
				"r": 0
			}
		},
		{
			"_id": "5e68b2c286f7745c3a0901f0",
			"_tpl": "5734779624597737e04bf329",
			"parentId": "5e68b2c286f7745c3a0901ee",
			"slotId": "main",
			"location": {
				"x": 1,
				"y": 0,
				"r": 0
			}
		},
		{
			"_id": "5e68b2c286f7745c3a0901f1",
			"_tpl": "5751487e245977207e26a315",
			"parentId": "5e68b2c286f7745c3a0901ee",
			"slotId": "main",
			"location": {
				"x": 2,
				"y": 0,
				"r": 0
			}
		},
		{
			"_id": "5e68b2c286f7745c3a0901f2",
			"_tpl": "573475fb24597737fb1379e1",
			"parentId": "5e68b2c286f7745c3a0901ee",
			"slotId": "main",
			"location": {
				"x": 3,
				"y": 0,
				"r": 0
			}
		}
	]
}