{
	"Id": "Lootable_00336",
	"IsStatic": true,
	"useGravity": true,
	"randomRotation": false,
	"Position": {
		"x": 0,
		"y": 0,
		"z": 0
	},
	"Rotation": {
		"x": 0,
		"y": 0,
		"z": 0
	},
	"IsGroupPosition": false,
	"GroupPositions": [],
	"Root": "5e68b2f486f7745c3b2444b3",
	"Items": [
		{
			"_id": "5e68b2f486f7745c3b2444b3",
			"_tpl": "5d6fd45b86f774317075ed43"
		},
		{
			"_id": "5e68b2f486f7745c3b2444b4",
			"_tpl": "57347c5b245977448d35f6e1",
			"parentId": "5e68b2f486f7745c3b2444b3",
			"slotId": "main",
			"location": {
				"x": 0,
				"y": 0,
				"r": 0
			}
		},
		{
			"_id": "5e68b2f486f7745c3b2444b5",
			"_tpl": "5733279d245977289b77ec24",
			"parentId": "5e68b2f486f7745c3b2444b3",
			"slotId": "main",
			"location": {
				"x": 1,
				"y": 0,
				"r": 0
			}
		},
		{
			"_id": "5e68b2f486f7745c3b2444b6",
			"_tpl": "5d4042a986f7743185265463",
			"parentId": "5e68b2f486f7745c3b2444b3",
			"slotId": "main",
			"location": {
				"x": 4,
				"y": 0,
				"r": 0
			}
		},
		{
			"_id": "5e68b2f486f7745c3b2444b7",
			"_tpl": "57347b8b24597737dd42e192",
			"parentId": "5e68b2f486f7745c3b2444b3",
			"slotId": "main",
			"location": {
				"x": 0,
				"y": 1,
				"r": 0
			}
		}
	]
}