{
	"Id": "loot_ammo_common (100)6547752",
	"IsStatic": false,
	"useGravity": true,
	"randomRotation": true,
	"Position": {
		"x": -105.541016,
		"y": -6.737,
		"z": -67.7379761
	},
	"Rotation": {
		"x": 0,
		"y": 0,
		"z": 0
	},
	"IsGroupPosition": false,
	"GroupPositions": [],
	"Root": "5e68b2f786f7741caf48cacf",
	"Items": [
		{
			"_id": "5e68b2f786f7741caf48cacf",
			"_tpl": "5737250c2459776125652acc"
		},
		{
			"_id": "5e68b2f786f7741caf48cad0",
			"_tpl": "573719df2459775a626ccbc2",
			"parentId": "5e68b2f786f7741caf48cacf",
			"slotId": "cartridges",
			"upd": {
				"StackObjectsCount": 16
			}
		}
	]
}