{
	"Id": "Lootable_00116",
	"IsStatic": true,
	"useGravity": true,
	"randomRotation": false,
	"Position": {
		"x": 0,
		"y": 0,
		"z": 0
	},
	"Rotation": {
		"x": 0,
		"y": 0,
		"z": 0
	},
	"IsGroupPosition": false,
	"GroupPositions": [],
	"Root": "5e68b2b286f7745c395bec77",
	"Items": [
		{
			"_id": "5e68b2b286f7745c395bec77",
			"_tpl": "578f8778245977358849a9b5"
		},
		{
			"_id": "5e68b2b286f7745c395bec78",
			"_tpl": "5a0f006986f7741ffd2fe484",
			"parentId": "5e68b2b286f7745c395bec77",
			"slotId": "main",
			"location": {
				"x": 0,
				"y": 0,
				"r": 0
			}
		}
	]
}