{
	"Id": "Lootable_00135",
	"IsStatic": true,
	"useGravity": true,
	"randomRotation": false,
	"Position": {
		"x": 0,
		"y": 0,
		"z": 0
	},
	"Rotation": {
		"x": 0,
		"y": 0,
		"z": 0
	},
	"IsGroupPosition": false,
	"GroupPositions": [],
	"Root": "5e68b2a386f7745c3804db52",
	"Items": [
		{
			"_id": "5e68b2a386f7745c3804db52",
			"_tpl": "578f87ad245977356274f2cc"
		},
		{
			"_id": "5e68b2a386f7745c3804db53",
			"_tpl": "5649aa744bdc2ded0b8b457e",
			"parentId": "5e68b2a386f7745c3804db52",
			"slotId": "main",
			"location": {
				"x": 0,
				"y": 0,
				"r": 0
			}
		},
		{
			"_id": "5e68b2a386f7745c3804db54",
			"_tpl": "5649ae4a4bdc2d1b2b8b4588",
			"parentId": "5e68b2a386f7745c3804db52",
			"slotId": "main",
			"location": {
				"x": 1,
				"y": 0,
				"r": 0
			}
		},
		{
			"_id": "5e68b2a386f7745c3804db55",
			"_tpl": "591af28e86f77414a27a9e1d",
			"parentId": "5e68b2a386f7745c3804db52",
			"slotId": "main",
			"location": {
				"x": 2,
				"y": 0,
				"r": 0
			}
		},
		{
			"_id": "5e68b2a386f7745c3804db56",
			"_tpl": "576a7c512459771e796e0e17",
			"parentId": "5e68b2a386f7745c3804db52",
			"slotId": "main",
			"location": {
				"x": 3,
				"y": 0,
				"r": 0
			}
		}
	]
}